Metadata-Version: 2.1
Name: torchrec-nightly-cpu
Version: 2022.5.12
Summary: Pytorch domain library for recommendation systems
Home-page: https://github.com/pytorch/torchrec
Author: TorchRec Team
Author-email: packages@pytorch.org
License: BSD-3
Keywords: pytorch,recommendation systems,sharding
Platform: UNKNOWN
Classifier: Development Status :: 4 - Beta
Classifier: Intended Audience :: Developers
Classifier: Intended Audience :: Science/Research
Classifier: License :: OSI Approved :: BSD License
Classifier: Programming Language :: Python :: 3
Classifier: Programming Language :: Python :: 3.7
Classifier: Topic :: Scientific/Engineering :: Artificial Intelligence
Requires-Python: >=3.7
License-File: LICENSE
Requires-Dist: arrow
Requires-Dist: attrs
Requires-Dist: certifi
Requires-Dist: charset-normalizer
Requires-Dist: cmake
Requires-Dist: Cython
Requires-Dist: distro
Requires-Dist: docker
Requires-Dist: docstring-parser
Requires-Dist: filelock
Requires-Dist: fsspec
Requires-Dist: hypothesis
Requires-Dist: idna
Requires-Dist: iopath
Requires-Dist: Jinja2
Requires-Dist: MarkupSafe
Requires-Dist: mypy-extensions
Requires-Dist: ninja
Requires-Dist: numpy
Requires-Dist: packaging
Requires-Dist: pandas
Requires-Dist: portalocker
Requires-Dist: pyarrow
Requires-Dist: pyDeprecate
Requires-Dist: pyparsing
Requires-Dist: pyre-extensions
Requires-Dist: python-dateutil
Requires-Dist: pytz
Requires-Dist: PyYAML
Requires-Dist: requests
Requires-Dist: scikit-build
Requires-Dist: six
Requires-Dist: sortedcontainers
Requires-Dist: tabulate
Requires-Dist: torchmetrics
Requires-Dist: torchx-nightly
Requires-Dist: tqdm
Requires-Dist: typing
Requires-Dist: typing-inspect
Requires-Dist: typing-extensions
Requires-Dist: urllib3
Requires-Dist: websocket-client
